Workbook

Sheet Notice
A1: Bilan d'eau du jardin sec - Liceo Franco Hondureno
A3: Classeur d'accompagnement du projet jardin sec, technologie cycle 4.
A4: Il sert en seance 5 de 5e, en seance 6 de 4e et en seances 3 et 5 de 3e.
A6: COMMENT L'UTILISER
A7: 1. Onglet Parametres : les eleves ne modifient QUE les cellules sur fond jaune, en bleu.
A8: Toutes les autres cellules du classeur sont des formules et se recalculent seules.
A9: 2. Onglet Bilan_eau : le resultat du projet, compare a l'objectif du cahier des charges.
A10: 3. Onglet Journal : coller ici le CSV exporte de la carte micro:bit receptrice.
A11: Une ligne d'exemple montre le format attendu. La supprimer avant de coller les vraies donnees.
A12: 4. Onglet Energie : le bilan energetique de la seance 2 de 3e.
A13: 5. Onglet Materiel : le budget du projet, a actualiser au moment de la demande d'achat.
A15: CODE COULEUR
... A29: ce qui explique les petits ecarts entre les chiffres des fiches et ceux du classeur.

Sheet Parametres
A1: Parametres du projet
A2: Les cellules jaunes sont les seules a modifier.
A4: Parametre | B4: Valeur | C4: Unite | D4: Origine de la donnee
A5: Longueur du couloir | B5: 12 | C5: m | D5: Releve au decametre, 5e seance 1
A6: Largeur du couloir | B6: 4 | C6: m | D6: Releve au decametre, 5e seance 1
A7: Largeur occupee par la haie | B7: 0.6 | C7: m | D7: Releve, 5e seance 1
A8: Largeur du passage a laisser libre | B8: 1.2 | C8: m | D8: Contrainte de circulation
A9: Nombre de jardinieres | B9: 8 | D9: Choix de la classe, 5e seance 1
A10: Longueur d'une jardiniere | B10: 1.2 | C10: m | D10: Cahier des charges, 5e seance 3
A11: Largeur d'une jardiniere | B11: 0.8 | C11: m | D11: Cahier des charges, 5e seance 3
A12: Duree de la saison seche | B12: 180 | C12: jours | D12: Graphique des precipitations, 5e seance 1
A13: Besoin d'un potager classique | B13: 5 | C13: L/m2/jour | D13: Documentation, 5e seance 1
A14: Objectif du cahier des charges | B14: 1 | C14: L/m2/jour | D14: Contrainte FC1
A15: Consommation mesuree du systeme | B15: 2.7 | C15: L/jour | D15: Releve du fut, 4e seance 6
A16: Arrosage manuel des temoins | B16: 6 | C16: L/jour | D16: Releve a l'arrosoir, 4e seance 6
A17: Surface de toiture captee | B17: 70 | C17: m2 | D17: Releve et plan, 4e seance 2
A18: Pluviometrie annuelle | B18: 900 | C18: mm | D18: Station meteorologique locale
A19: Coefficient de recuperation | B19: 0.8 | D19: Documentation, 4e seance 2
A20: Volume utile d'un fut | B20: 200 | C20: L | D20: Fiche fournisseur
A21: Debit d'un goutteur | B21: 2 | C21: L/h | D21: Mesure au chronometre, 4e seance 1
A22: Prix du litre d'eau du reseau | B22: 0.03 | C22: lempira | D22: Facture de l'etablissement

Sheet Bilan_eau
A1: Bilan d'eau de la saison seche
A3: Grandeur | B3: Valeur | C3: Unite | D3: Formule et commentaire
A4: Surface totale de la cour | B4: =Parametres!B5*Parametres!B6 -> 48 | C4: m2 | D4: longueur x largeur
A5: Emprise de la haie | B5: =Parametres!B5*Parametres!B7 -> 7.2 | C5: m2 | D5: longueur x largeur de haie
A6: Passage a laisser libre | B6: =Parametres!B5*Parametres!B8 -> 14.4 | C6: m2 | D6: longueur x largeur de passage
A7: Surface plantable | B7: =B4-B5-B6 -> 26.4 | C7: m2 | D7: ce qui reste apres la haie et le passage
A8: Surface reellement cultivee | B8: =Parametres!B9*Parametres!B10*Parametres!B11 -> 7.68 | C8: m2 | D8: nombre de jardinieres x longueur x largeur
A10: Consommation du systeme | B10: =Parametres!B15*Parametres!B12 -> 486 | C10: L | D10: consommation par jour x duree de la saison seche
A11: Consommation de l'arrosage manuel | B11: =Parametres!B16*Parametres!B12 -> 1080 | C11: L | D11: temoins arroses a l'arrosoir
A12: Consommation d'un potager classique | B12: =Parametres!B13*B8*Parametres!B12 -> 6912 | C12: L | D12: besoin par m2 x surface cultivee x duree
A13: Economie face au potager classique | B13: =B12-B10 -> 6426 | C13: L | D13: difference des deux precedentes
A14: Economie en pourcentage | B14: =1-B10/B12 -> 0.9296875 | D14: part economisee
A16: Consommation par m2 et par jour | B16: =B10/(B8*Parametres!B12) -> 0.3515625 | C16: L/m2/jour | D16: grandeur comparee a la contrainte FC1
A17: Objectif du cahier des charges | B17: =Parametres!B14 -> 1 | C17: L/m2/jour | D17: contrainte FC1
A18: Contrainte FC1 | B18: =IF(B16<=B17,"RESPECTEE","NON RESPECTEE") -> RESPECTEE | D18: comparaison automatique
A19: Marge par rapport a l'objectif | B19: =1-B16/B17 -> 0.6484375 | D19: part de l'objectif non consommee
A21: Recolte annuelle possible sur la toiture | B21: =Parametres!B17*Parametres!B18*Parametres!B19 -> 50400 | C21: L | D21: surface de toiture x pluviometrie x coefficient
A22: Part de la recolte utilisee par le jardin | B22: =B10/B21 -> 0.0096428571 | D22: consommation rapportee a la recolte
A23: Autonomie d'un fut plein, a la consommation mesuree | B23: =Parametres!B20/Parametres!B15 -> 74.074074 | C23: jours | D23: volume du fut divise par la consommation quotidienne
A24: Futs necessaires sans aucune pluie | B24: =ROUNDUP(B10/Parametres!B20,0) -> 3 | D24: consommation totale divisee par le volume d'un fut
A26: Duree d'arrosage quotidienne, a la consommation mesuree | B26: =Parametres!B15/(Parametres!B9*Parametres!B21)*60 -> 10.125 | C26: min | D26: consommation divisee par le debit total
A27: Eau potable prelevee sur le reseau | B27: 0 | C27: L | D27: toute l'eau vient de la pluie recuperee
A28: Valeur de l'eau economisee | B28: =B13*Parametres!B22 -> 192.78 | C28: lempiras | D28: economie x prix du litre

Sheet Journal
A1: Journal de donnees de la carte receptrice
A2: Coller ici le CSV exporte de MY_DATA.HTM. La ligne 5 est un exemple, la supprimer avant de coller.
A4: Temps (s) | B4: Jardiniere | C4: Humidite (%) | D4: Arrosage | E4: Heure | F4: Etat | H4: Analyse du journal
A5: 1800 | B5: 3 | C5: 34 | D5: 0 | E5: =A5/3600 -> 0.5 | F5: =IF(C5<0,"capteur en defaut",IF(D5=1,"arrosage en cours","au repos")) -> au repos | H5: Nombre de mesures | I5: =COUNT(A5:A200) -> 1
E6: =IF(A6="","",A6/3600) | F6: =IF(A6="","",IF(C6<0,"capteur en defaut",IF(D6=1,"arrosage en cours","au repos"))) | H6: Nombre d'arrosages | I6: =SUMIFS(D5:D200,D5:D200,1) -> 0
E7: =IF(A7="","",A7/3600) | F7: =IF(A7="","",IF(C7<0,"capteur en defaut",IF(D7=1,"arrosage en cours","au repos"))) | H7: Humidite moyenne | I7: =IFERROR(AVERAGEIF(C5:C200,">=0"),0) -> 34
E8: =IF(A8="","",A8/3600) | F8: =IF(A8="","",IF(C8<0,"capteur en defaut",IF(D8=1,"arrosage en cours","au repos"))) | H8: Humidite minimale | I8: =IFERROR(MIN(C5:C200),0) -> 34
E9: =IF(A9="","",A9/3600) | F9: =IF(A9="","",IF(C9<0,"capteur en defaut",IF(D9=1,"arrosage en cours","au repos"))) | H9: Humidite maximale | I9: =IFERROR(MAX(C5:C200),0) -> 34
E10: =IF(A10="","",A10/3600) | F10: =IF(A10="","",IF(C10<0,"capteur en defaut",IF(D10=1,"arrosage en cours","au repos"))) | H10: Mesures en defaut | I10: =COUNTIF(C5:C200,"<0") -> 0
E11: =IF(A11="","",A11/3600) | F11: =IF(A11="","",IF(C11<0,"capteur en defaut",IF(D11=1,"arrosage en cours","au repos"))) | H11: Duree couverte (heures) | I11: =IFERROR((MAX(A5:A200)-MIN(A5:A200))/3600,0) -> 0
E12: =IF(A12="","",A12/3600) | F12: =IF(A12="","",IF(C12<0,"capteur en defaut",IF(D12=1,"arrosage en cours","au repos")))
E13: =IF(A13="","",A13/3600) | F13: =IF(A13="","",IF(C13<0,"capteur en defaut",IF(D13=1,"arrosage en cours","au repos")))
E14: =IF(A14="","",A14/3600) | F14: =IF(A14="","",IF(C14<0,"capteur en defaut",IF(D14=1,"arrosage en cours","au repos")))
E15: =IF(A15="","",A15/3600) | F15: =IF(A15="","",IF(C15<0,"capteur en defaut",IF(D15=1,"arrosage en cours","au repos")))
E16: =IF(A16="","",A16/3600) | F16: =IF(A16="","",IF(C16<0,"capteur en defaut",IF(D16=1,"arrosage en cours","au repos")))
E17: =IF(A17="","",A17/3600) | F17: =IF(A17="","",IF(C17<0,"capteur en defaut",IF(D17=1,"arrosage en cours","au repos")))
E18: =IF(A18="","",A18/3600) | F18: =IF(A18="","",IF(C18<0,"capteur en defaut",IF(D18=1,"arrosage en cours","au repos")))
E19: =IF(A19="","",A19/3600) | F19: =IF(A19="","",IF(C19<0,"capteur en defaut",IF(D19=1,"arrosage en cours","au repos")))
E20: =IF(A20="","",A20/3600) | F20: =IF(A20="","",IF(C20<0,"capteur en defaut",IF(D20=1,"arrosage en cours","au repos")))
E21: =IF(A21="","",A21/3600) | F21: =IF(A21="","",IF(C21<0,"capteur en defaut",IF(D21=1,"arrosage en cours","au repos")))
E22: =IF(A22="","",A22/3600) | F22: =IF(A22="","",IF(C22<0,"capteur en defaut",IF(D22=1,"arrosage en cours","au repos")))
E23: =IF(A23="","",A23/3600) | F23: =IF(A23="","",IF(C23<0,"capteur en defaut",IF(D23=1,"arrosage en cours","au repos")))
... E59: =IF(A59="","",A59/3600) | F59: =IF(A59="","",IF(C59<0,"capteur en defaut",IF(D59=1,"arrosage en cours","au repos")))

Sheet Energie
A1: Bilan energetique du systeme
A3: Grandeur | B3: Valeur | C3: Unite | D3: Origine ou formule
A4: Tension d'alimentation du micro:bit | B4: 3 | C4: V | D4: mesure, 3e seance 2
A5: Courant en veille | B5: 0.015 | C5: A | D5: mesure au multimetre, 3e seance 2
A6: Tension de l'electrovanne | B6: 6 | C6: V | D6: fiche du composant
A7: Courant pendant l'arrosage | B7: 0.485 | C7: A | D7: mesure au multimetre
A8: Nombre d'arrosages par jour | B8: 4 | D8: reglage du programme
A9: Duree d'un arrosage | B9: 90 | C9: s | D9: reglage du programme
A10: Puissance du panneau solaire | B10: 2 | C10: W | D10: fiche du composant
A11: Heures d'ensoleillement equivalentes | B11: 5 | C11: h/jour | D11: donnee locale
A12: Rendement de charge | B12: 0.7 | D12: documentation
A13: Capacite de l'accumulateur | B13: 2600 | C13: mAh | D13: fiche du composant
A14: Tension de l'accumulateur | B14: 3.7 | C14: V | D14: fiche du composant
A15: Autonomie exigee | B15: 7 | C15: jours | D15: contrainte FP2
A17: Puissance en veille | B17: =B4*B5 -> 0.045 | C17: W | D17: tension x courant
A18: Puissance pendant l'arrosage | B18: =B17+B6*B7 -> 2.955 | C18: W | D18: micro:bit plus electrovanne
A19: Duree d'arrosage par jour | B19: =B8*B9/3600 -> 0.1 | C19: h | D19: nombre x duree, converti en heures
A20: Energie de veille par jour | B20: =B17*(24-B19) -> 1.0755 | C20: Wh | D20: puissance x duree
A21: Energie d'arrosage par jour | B21: =B18*B19 -> 0.2955 | C21: Wh | D21: puissance x duree
A22: Besoin total par jour | B22: =B20+B21 -> 1.371 | C22: Wh | D22: somme des deux precedentes
A23: Part de la veille | B23: =B20/B22 -> 0.78446389 | D23: la veille pese plus que l'arrosage
A25: Production du panneau par jour | B25: =B10*B11 -> 10 | C25: Wh | D25: puissance x heures equivalentes
A26: Production utile apres pertes | B26: =B25*B12 -> 7 | C26: Wh | D26: production x rendement de charge
A27: Rapport production sur consommation | B27: =B26/B22 -> 5.1057622 | D27: marge de securite
A28: Energie stockee dans l'accumulateur | B28: =B13/1000*B14 -> 9.62 | C28: Wh | D28: capacite en Ah x tension
A29: Autonomie sans soleil | B29: =B28/B22 -> 7.0167761 | C29: jours | D29: energie stockee divisee par le besoin
A30: Contrainte FP2 | B30: =IF(B29>=B15,"RESPECTEE","NON RESPECTEE") -> RESPECTEE | D30: comparaison automatique

Sheet Materiel
A1: Budget du projet
A2: Prix indicatifs releves a Tegucigalpa. A actualiser au moment de la demande d'achat.
A4: Poste | B4: Article | C4: Quantite | D4: Prix unitaire (L) | E4: Total (L)
A5: Structure | B5: Palettes bois traitees HT | C5: 12 | D5: 80 | E5: =C5*D5 -> 960
A6: Structure | B6: Vis a bois 5x60, boite de 200 | C6: 2 | D6: 180 | E6: =C6*D6 -> 360
A7: Structure | B7: Equerres galvanisees | C7: 32 | D7: 12 | E7: =C7*D7 -> 384
A8: Structure | B8: Geotextile, rouleau 10 m | C8: 1 | D8: 450 | E8: =C8*D8 -> 450
A9: Structure | B9: Terre vegetale, sac de 40 L | C9: 20 | D9: 65 | E9: =C9*D9 -> 1300
A10: Structure | B10: Compost, sac de 40 L | C10: 8 | D10: 90 | E10: =C10*D10 -> 720
A11: Structure | B11: Paillage ecorce, sac | C11: 10 | D11: 55 | E11: =C11*D11 -> 550
A12: Structure | B12: Peinture exterieure, 1 L | C12: 4 | D12: 320 | E12: =C12*D12 -> 1280
A13: Plantes | B13: Plants et semences | C13: 1 | D13: 1500 | E13: =C13*D13 -> 1500
A14: Eau | B14: Fut plastique 200 L avec couvercle | C14: 1 | D14: 950 | E14: =C14*D14 -> 950
A15: Eau | B15: Gouttiere PVC 3 m et coudes | C15: 4 | D15: 210 | E15: =C15*D15 -> 840
A16: Eau | B16: Robinet de puisage et passe-cloison | C16: 1 | D16: 180 | E16: =C16*D16 -> 180
... A30: Commande | B30: Multimetre | C30: 2 | D30: 450 | E30: =C30*D30 -> 900
D32: Total general | E32: =SUM(E5:E30) -> 21254
D33: Taux de change L pour 1 EUR | E33: 28.5
D34: Total en euros | E34: =E32/E33 -> 745.75439
D36: Sous-total Structure | E36: =SUMIF($A$5:$A$30,"Structure",$E$5:$E$30) -> 6004
D37: Sous-total Plantes | E37: =SUMIF($A$5:$A$30,"Plantes",$E$5:$E$30) -> 1500
D38: Sous-total Eau | E38: =SUMIF($A$5:$A$30,"Eau",$E$5:$E$30) -> 3450
D39: Sous-total Commande | E39: =SUMIF($A$5:$A$30,"Commande",$E$5:$E$30) -> 10300
